[
    {
        "sid": 116503,
        "name": "",
        "sname": "마이크로 딥 클렌징 폼",
        "description": "",
        "sdescription": "98.8% 미세먼지 세정은 기본! 모공 속 노폐물을 씻어내어 블랙헤드 개선까지 해주는 딥 클렌징 폼\r\n\r\n- 말캉한 자연 유래 곤약을 잘게 쪼개어 넣어, 별도의 클렌징 브러쉬 없이도 부드럽게 모공을 클렌징\r\n- 동물성원료, 광물성오일 등 7가지 유해한 성분을 첨가하지 않은 7 FREE\r\n- 안자극 대체 테스트 완료\r\n- 미세먼지를 자석처럼 끌어당겨 강력 딥 클렌징\r\n- 쫀쫀 탄력 마이크로 거품으로 촉촉 산뜻 클렌징 ",
        "category": {
            "first_category_id": 7,
            "first_category_name": "làm sạch",
            "first_category_en_name": "cleansing",
            "second_category_id": 32,
            "second_category_name": "rửa mặt",
            "second_category_en_name": "facial cleanser",
            "third_category_id": 112,
            "third_category_name": "sữa rửa mặt tạo bọt",
            "third_category_en_name": "cleansing foam"
        }
    },
    {
        "sid": 104675,
        "name": "",
        "sname": "에브리데이 선스틱 카렌듈라 [SPF50+/PA++++]",
        "description": "",
        "sdescription": "강력한 자외선 차단은 물론 미세먼지로부터 피부를 보호해주는 보송한 사용감의 선스틱\n\n- 카렌듈라 콤플렉스가 자외선에 손상된 피부를 진정\n- 자외선, 미세먼지, 피부건조 3중 차단\n- 덧발라도 끈적이지 않는 보송함",
        "category": {
            "first_category_id": 9,
            "first_category_name": "chống nắng",
            "first_category_en_name": "sun care",
            "second_category_id": 43,
            "second_category_name": "thanh chống nắng",
            "second_category_en_name": "sun stick",
            "third_category_id": null,
            "third_category_name": null,
            "third_category_en_name": null
        }
    },
    {
        "sid": 79104,
        "name": "",
        "sname": "트리플 멀티 클렌징 폼",
        "description": "",
        "sdescription": "* 2017년 7월 패키지 리뉴얼 된 제품입니다.\r\n\r\n창포물로 세안한 듯 개운하게, 폼 하나만으로 메이크업ㆍ선크림ㆍ각질까지 한 번에 지워주는 3 in 1 멀티 클렌징\r\n\r\n1. 빠르고 간편한 클렌징\r\n1차 세안 필요 없이, 폼 하나만으로 선크림과 메이크업까지 지워줍니다.\r\n\r\n2. 산뜻한 창포물 클렌징\r\n지복합성 피부도 개운하게 세안을 마무리할 수 있는 상쾌한 타입입니다.",
        "category": {
            "first_category_id": 7,
            "first_category_name": "làm sạch",
            "first_category_en_name": "cleansing",
            "second_category_id": 32,
            "second_category_name": "rửa mặt",
            "second_category_en_name": "facial cleanser",
            "third_category_id": 112,
            "third_category_name": "sữa rửa mặt tạo bọt",
            "third_category_en_name": "cleansing foam"
        }
    },
    {
        "sid": 68065,
        "name": "",
        "sname": "연꽃 마이크로 마스크 투 폼",
        "description": "",
        "sdescription": "* 2017년 7월 패키지 리뉴얼 된 제품입니다.\r\n\r\n천연 핑크 클레이가 각질과 블랙헤드를 제거하고, 물을 묻히면 조밀한 거품으로 변하여 모공 속까 지 꼼꼼하게 씻어내는 상쾌한 딥 클렌징 마스크\r\n\r\n1. 연꽃 성분의 다양화\r\n 꽃부터 뿌리까지 버릴 것이 하나도 없이 활용되는 연꽃, 기존 연꽃 추출물에 연 꽃 배아 추출물과 연근 파우더를 더하여 영양 및 수분 공급 개선\r\n\r\n2. 연꽃의 뛰어난 정화력\r\n 연꽃의 정화작용을 일으키는 '연꽃잎 효과'에서 피부 정화의 혁신 기술을 착안하 여 연꽃잎 표면과 유사한 구조의 울트라파인 폴리머 구현\r\n\r\n3. LOTUS ANTI-PM COMPLEX ™\r\n 미네랄이 풍부한 머드와 로터스 안티-피엠 콤플렉스™가 만나 모공 깊숙이 파고든 미세먼지 까지 개운하게 씻어내고 모공을 수렴",
        "category": {
            "first_category_id": 7,
            "first_category_name": "làm sạch",
            "first_category_en_name": "cleansing",
            "second_category_id": 32,
            "second_category_name": "rửa mặt",
            "second_category_en_name": "facial cleanser",
            "third_category_id": 112,
            "third_category_name": "sữa rửa mặt tạo bọt",
            "third_category_en_name": "cleansing foam"
        }
    },
    {
        "sid": 106968,
        "name": "",
        "sname": "로즈워터 수딩젤",
        "description": "",
        "sdescription": "장미수 90.81%를 듬뿍 담아 촉촉하고 흡수가 빠른 멀티 사용 수딩젤\r\n\r\n- 다마스크 장미수의 진정 보습 효능\r\n아침 이슬을 맞고 자란 다마스크 장미를 골라 담아 피부에 탁월한 진정 및 보습 효능을 선사합니다.\r\n\r\n- 대용량 멀티 사용 수딩젤\r\n얼굴, 헤어, 바디 등 건조하고 지친 부위를 장미 향과 함께 시원하게 진정시켜줍니다.\r\n\r\n- 7-FREE\r\n동물성원료, 광물성오일, 폴리아크릴아마이드, 이미다졸리디닐우레아, 트리에탄올아민, 타르색소, PEG계면활성제",
        "category": {
            "first_category_id": 9,
            "first_category_name": "chống nắng",
            "first_category_en_name": "sun care",
            "second_category_id": 48,
            "second_category_name": "nhả nắng",
            "second_category_en_name": "after sun",
            "third_category_id": 152,
            "third_category_name": "gel nhả nắng",
            "third_category_en_name": "soothing gel"
        }
    },
    {
        "sid": 104143,
        "name": "",
        "sname": "에브리데이 아쿠아 선크림 [SPF50+/PA++++]",
        "description": "",
        "sdescription": "일상 속 강한 자외선으로부터 피부를 강력하게 보호하고, 터져나오는 수분감으로 피부를 촉촉하게 해주는 수분 폭탄 데일리 선크림\r\n\r\n- UVA, UVB 강력한 차단\r\n업그레이드 된 PA 차단지수로 (4+) 자외선으로부터 피부를 강력하게 보호\r\n\r\n- 카렌듈라 콤플렉스™\r\n카렌듈라 꽃 추출물 + 마데카소사이드 성분으로 자외선에 노출되는 피부를 건강하게 케어\r\n\r\n- 목화 추출물의 미세먼지 경감효과\r\n피부 장벽을 손상시키고 노화를 촉진하는 원인인 미세먼지의 영향 경감 효과\r\n\r\n- 촉촉한 워터 스플래시 제형\r\n물방울이 터지는 워터 스플래시 제형이 산뜻하고 부드럽게 발려, 피부에 기분 좋은 촉촉함을 선사",
        "category": {
            "first_category_id": 9,
            "first_category_name": "chống nắng",
            "first_category_en_name": "sun care",
            "second_category_id": 41,
            "second_category_name": "kem chống nắng",
            "second_category_en_name": "suncreen",
            "third_category_id": 142,
            "third_category_name": "sữa chống nắng",
            "third_category_en_name": "mild sunscreen"
        }
    },
    {
        "sid": 94895,
        "name": "",
        "sname": "마이크로 클렌징 폼",
        "description": "",
        "sdescription": "* 2017년 7월 리뉴얼 된 제품입니다.\r\n\r\n초미세먼지까지 말끔하게 씻어내고, 피부보습인자는 그대로 지켜주어 건강하고 환한 얼굴로 가꾸어주는 촉촉하느 브라이트닝 클렌징 폼\r\n\r\n1. 연꽃 성분의 다양화\r\n 꽃부터 뿌리까지 버릴 것이 하나도 없이 활용되는 연꽃, 기존 연꽃 추출물에 연꽃 배아 추출물과 연근 파우더를 더하여 영양 및 수분 공급 개선\r\n\r\n2.연꽃의 뛰어난 정화력\r\n연꽃의 자정작용을 일으키는 '연꽃잎 효과'에서 피부 정화의 혁신 기술을 착안하여 연꽃잎 표면과 유사한 구조의 울트라파인 폴리머 구현\r\n\r\n3.lotus anti-pm complex tm\r\n세가지 연꽃 성분과 양이온 폴리머가 함유된 콤플렉스가 미세먼지를 자석의 원리로 강력하게 끌어당겨 탈락시키고, 마일드한 사용감과 브라이트닝한 효과 부여",
        "category": {
            "first_category_id": 7,
            "first_category_name": "làm sạch",
            "first_category_en_name": "cleansing",
            "second_category_id": 32,
            "second_category_name": "rửa mặt",
            "second_category_en_name": "facial cleanser",
            "third_category_id": 112,
            "third_category_name": "sữa rửa mặt tạo bọt",
            "third_category_en_name": "cleansing foam"
        }
    },
    {
        "sid": 107923,
        "name": "",
        "sname": "아쿠아 필 필링젤",
        "description": "",
        "sdescription": "피부에 쌓인 각질에 흡착하여 밀어 내는 각질 보습 필링젤\r\n\r\n1 매실-효소 2스텝 필링\r\n매실 성분을 함유한 포뮬라가 묵은 각질을 불려주고, 식물로부터 얻은 효소 성분이 피부 턴오버를 도와 효과적으로 각질을 제거하여 투명한 피부결로 가꾸어줍니다.\r\n\r\n2 매화 추출물의 피부 보습 효과\r\n매화 성분이 각질이 정돈된 피부에 풍부한 영양과 수분을 전달해 피부를 촉촉하게 유지시켜줍니다.\r\n\r\n3 AHA 마일드 필링\r\n각질 제거에 효과적인 AHA 성분이 함유되어 묵은 각질을 탈락시키는 데 도움을 줍니다.\r\n\r\n4 4-FREE\r\n동물성원료, 광물성오일, 합성색소, 트리에탄올아민",
        "category": {
            "first_category_id": 7,
            "first_category_name": "làm sạch",
            "first_category_en_name": "cleansing",
            "second_category_id": 35,
            "second_category_name": "tẩy da chết",
            "second_category_en_name": "exfoliator",
            "third_category_id": 125,
            "third_category_name": "tẩy da chết dạng kì",
            "third_category_en_name": "peeling gel"
        }
    },
    {
        "sid": 93969,
        "name": "",
        "sname": "트리플 멀티 클렌징 크림",
        "description": "",
        "sdescription": "가볍고 부드러운 마사지로 메이크업을 녹여내는 크립 타입의 간편 워셔블 클렌저\r\n\r\n1. 끈적임 없이 가볍고 부드러운 마사지감을 주고 수용성 보습성분이 피부에 촉촉함을 남겨줍니다.\r\n\r\n2. 가볍게 퍼지는 액상 클렌징 성분이 피부를 산뜻하게 가꾸어줍니다.\r\n\r\n3. 안자극 테스트를 완료하여 부담없이 안전하게 사용할 수 있습니다.",
        "category": {
            "first_category_id": 7,
            "first_category_name": "làm sạch",
            "first_category_en_name": "cleansing",
            "second_category_id": 33,
            "second_category_name": "tẩy trang",
            "second_category_en_name": "makeup remover",
            "third_category_id": 121,
            "third_category_name": "kem tẩy trang",
            "third_category_en_name": "cleansing cream"
        }
    },
    {
        "sid": 93971,
        "name": "",
        "sname": "트리플 멀티 클렌징 티슈",
        "description": "",
        "sdescription": "미끌거리지 않고 산뜻하게 마무리되며, 빠르고 간편하게 메이크업을 제거해주는 산뜻한 클렌징 티슈\r\n\r\n01. 미끌거리지 않고 산뜻하게 마무리되며, 빠르고 간편하게 메이크업을 제거해줍니다.\r\n\r\n02. 수용성 클렌징액이 진한 메이크업까지 딥 클렌징해줍니다.\r\n\r\n03. 부담없는 용량과 가격으로, 매일매일 부드럽게 티슈로 클렌징을 가능하게 해줍니다.\r\n\r\n04. 얼굴전체는 물론 포인트 메이크업까지 꼼꼼하게 제거해 줄 수 있는 충분한 사이즈 입니다.",
        "category": {
            "first_category_id": 7,
            "first_category_name": "làm sạch",
            "first_category_en_name": "cleansing",
            "second_category_id": 33,
            "second_category_name": "tẩy trang",
            "second_category_en_name": "makeup remover",
            "third_category_id": 122,
            "third_category_name": "khăn ướt tẩy trang",
            "third_category_en_name": "cleansing tissue"
        }
    },
    {
        "sid": 104674,
        "name": "",
        "sname": "에브리데이 톤업 선베이스[SPF35/PA++]",
        "description": "",
        "sdescription": "촉촉하면서도 보송한 사용감으로 피부톤을 환하게 보정시켜주고 생활 자외선은 차단 시켜주는 미백 & 자외선 2중 기능성 선베이스\r\n\r\n1. 카렌듈라 콤플렉스™\r\n- 카렌듈라 꽃 추출물 + 마데카소사이드 성분으로 자외선에 노출되는 피부를 건강하게 케어\r\n\r\n2. 목화 추출물의 미세먼지 경감효과\r\n- 피부 장벽을 손상시키고 노화를 촉진하는 원인인 미세먼지의 영향 경감 효과\r\n\r\n3. Silky bright – UP 콤플렉스\r\n- 다공성 구상 파우더가 함유되어 보송보송한 마무리감을 선사하고, 피부 사이사이에 광채를 촘촘하게 채워주어 자연스러운 톤업 연출",
        "category": {
            "first_category_id": 9,
            "first_category_name": "chống nắng",
            "first_category_en_name": "sun care",
            "second_category_id": 45,
            "second_category_name": "kem lót chống nắng",
            "second_category_en_name": "sun base",
            "third_category_id": null,
            "third_category_name": null,
            "third_category_en_name": null
        }
    },
    {
        "sid": 85603,
        "name": "",
        "sname": "페탈 스파 클렌징 오일",
        "description": "",
        "sdescription": "* 2017년 7월 패키지 리뉴얼 된 제품입니다.\r\n\r\n롤링 시 발생하는 온열감의 오일이 모공 속 노폐물까지 말끔하게 제거해주는 따뜻한 클렌징 오일\r\n\r\n1. 온열감 있는 오일에 손의 체온이 더해져 스팀타월 효과\r\n\r\n2. 모공 속 노폐물까지 말끔하게 제거\r\n\r\n3. 보습감 넘치는 히팅 클렌징 오일",
        "category": {
            "first_category_id": 7,
            "first_category_name": "làm sạch",
            "first_category_en_name": "cleansing",
            "second_category_id": 33,
            "second_category_name": "tẩy trang",
            "second_category_en_name": "makeup remover",
            "third_category_id": 118,
            "third_category_name": "dầu tẩy trang",
            "third_category_en_name": "cleansing oil"
        }
    },
    {
        "sid": 85601,
        "name": "",
        "sname": "페탈 스파 클렌징밤",
        "description": "",
        "sdescription": "* 2017년 7월 패키지 리뉴얼 된 제품입니다.\r\n\r\n피부에 닿는 순간 오일로 녹는 젤리 제형이 메이크업을 깔끔하게 지워주는 마사지 겸용 클렌징 밤\r\n\r\n1. 피부에 닿는 순간 오일로 녹는 새로운 셔벗 제형\r\n\r\n2. 마사지를 받는 것처럼 부드러운 멜팅력을 제공\r\n\r\n3. 밤 오일에서 물이 닿으면 우유빛으로 변화하는 제형으로 메이크업 잔여물을 말끔하게 제거하여 산뜻한 마무리 감 제공",
        "category": {
            "first_category_id": 7,
            "first_category_name": "làm sạch",
            "first_category_en_name": "cleansing",
            "second_category_id": 33,
            "second_category_name": "tẩy trang",
            "second_category_en_name": "makeup remover",
            "third_category_id": 117,
            "third_category_name": "sáp tẩy trang",
            "third_category_en_name": "cleansing balm"
        }
    },
    {
        "sid": 107922,
        "name": "",
        "sname": "포어 클린 블랙헤드 스틱",
        "description": "",
        "sdescription": "쓱싹 문지르면 모공 속에 쌓인 블랙헤드가 깨끗하게 제거되는 블랙헤드 클렌징 스틱\r\n\r\n1 어성초 팅크처\r\n어성초 팅크처가 과도하게 분비된 피지를 정돈하고 모공을 효과적으로 수렴\r\n\r\n2 서해안 머드\r\n서해안 머드 파우더가 모공 속 노폐물과 피지를 강력하게 흡착\r\n\r\n3 어성초 잎 스크럽\r\n어성초 잎 스크럽이 블랙헤드, 화이트헤드, 각질을 깨끗하게 제거",
        "category": {
            "first_category_id": 7,
            "first_category_name": "làm sạch",
            "first_category_en_name": "cleansing",
            "second_category_id": 35,
            "second_category_name": "tẩy da chết",
            "second_category_en_name": "exfoliator",
            "third_category_id": 125,
            "third_category_name": "tẩy da chết dạng kì",
            "third_category_en_name": "peeling gel"
        }
    },
    {
        "sid": 85600,
        "name": "",
        "sname": "페탈 스파 오일 투 폼",
        "description": "",
        "sdescription": "* 2017년 7월 패키지 리뉴얼 된 제품입니다.\r\n\r\n오일이 메이크업을 부드럽게 녹여주고 물을 묻히면 거품이 발생하여 쉽고 빠른 클렌징이 가능한 오일 투 폼\r\n\r\n1. 오일이 메이크업을 부드럽게 녹여줌\r\n\r\n2. 물과 만나면 거품이 나는 transforming gel cleanser\r\n\r\n3. 베이스메이크업 시 이중 세안 필요없이 클렌징 마무리 가능",
        "category": {
            "first_category_id": 7,
            "first_category_name": "làm sạch",
            "first_category_en_name": "cleansing",
            "second_category_id": 32,
            "second_category_name": "rửa mặt",
            "second_category_en_name": "facial cleanser",
            "third_category_id": 112,
            "third_category_name": "sữa rửa mặt tạo bọt",
            "third_category_en_name": "cleansing foam"
        }
    },
    {
        "sid": 6648,
        "name": "",
        "sname": "내츄럴 필링젤",
        "description": "",
        "sdescription": "피부 손상 없이 묵은 각질을 부드럽게 제거해 맑고 투명한 피부로 가꾸어주는 필링젤. 풍부한 수분을 머금은 투명 젤이 피부에 부드럽게 도포되어 손에 의한 피부 자극을 최소화하고 피부를 부드럽게 감싸줍니다. 피부 속 독소와 묵은 각질을 흡착하여 눈에 보이는 덩어리로 만들어 피부로부터 제거해줍니다. 수련꽃 추출물과 라멘더 꽃수를 함유하여 피부를 진정시켜주고, 뛰어난 보습을 전달합니다.",
        "category": {
            "first_category_id": 7,
            "first_category_name": "làm sạch",
            "first_category_en_name": "cleansing",
            "second_category_id": 35,
            "second_category_name": "tẩy da chết",
            "second_category_en_name": "exfoliator",
            "third_category_id": 125,
            "third_category_name": "tẩy da chết dạng kì",
            "third_category_en_name": "peeling gel"
        }
    }
]