{
    "Code": 200,
    "Data": [{
            "id": 10453,
            "thumbnail": "https://image.brandi.me/cproduct/2020/04/16/15535495_1587016824_image1_M.jpg",
            "name": "Máy nghiền đơn Saem Saemmul 5g (Chọn 1)",
            "sale_price": 4500,
            "sale_percent": 10,
            "purchase_count": 55,
            "price": 5000,
            "productEtcInfo": {},
            "seller": {
                "address1": "",
                "address2": "",
                "bookmark_count": 0,
                "business_info": {
                    "business_code": "",
                    "business_name": "",
                    "mail_order_business_code": "",
                    "representative_name": ""
                },
                "email": "",
                "en_name": "",
                "id": "",
                "image_url": "",
                "name": "",
                "operation_time": "",
                "tags": null,
                "telephone": "",
                "text": "",
                "type": {
                    "id": "",
                    "name": ""
                }
            },
            "add_info": null,
            "sid": 15535495
        },
        {
            "id": 10456,
            "thumbnail": "https://image.brandi.me/cproduct/2019/10/04/9503408_1570163813_image1_M.jpg",
            "name": "[McQueen New York_MQNY] Son môi hoa Lucida",
            "sale_price": 4940,
            "sale_percent": 81,
            "purchase_count": 355,
            "price": 26000,
            "productEtcInfo": {},
            "seller": {
                "address1": "",
                "address2": "",
                "bookmark_count": 0,
                "business_info": {
                    "business_code": "",
                    "business_name": "",
                    "mail_order_business_code": "",
                    "representative_name": ""
                },
                "email": "",
                "en_name": "",
                "id": "",
                "image_url": "",
                "name": "",
                "operation_time": "",
                "tags": null,
                "telephone": "",
                "text": "",
                "type": {
                    "id": "",
                    "name": ""
                }
            },
            "add_info": null,
            "sid": 9503408
        },
        {
            "id": 10450,
            "thumbnail": "https://image.brandi.me/cproduct/2020/04/02/15127751_1585785769_image1_M.jpg",
            "name": "[Tôi là Mimi] MỚI Tôi đánh dấu vào Talk Trip Trip",
            "sale_price": 4950,
            "sale_percent": 67,
            "purchase_count": 214,
            "price": 15000,
            "productEtcInfo": {},
            "seller": {
                "address1": "",
                "address2": "",
                "bookmark_count": 0,
                "business_info": {
                    "business_code": "",
                    "business_name": "",
                    "mail_order_business_code": "",
                    "representative_name": ""
                },
                "email": "",
                "en_name": "",
                "id": "",
                "image_url": "",
                "name": "",
                "operation_time": "",
                "tags": null,
                "telephone": "",
                "text": "",
                "type": {
                    "id": "",
                    "name": ""
                }
            },
            "add_info": null,
            "sid": 15127751
        },
        {
            "id": 10472,
            "thumbnail": "https://image.brandi.me/cproduct/2019/12/24/12804181_1577179319_image1_M.jpg",
            "name": "Hoa hồng cũ KB00078",
            "sale_price": 5390,
            "purchase_count": 159,
            "price": 5390,
            "productEtcInfo": {},
            "seller": {
                "address1": "",
                "address2": "",
                "bookmark_count": 0,
                "business_info": {
                    "business_code": "",
                    "business_name": "",
                    "mail_order_business_code": "",
                    "representative_name": ""
                },
                "email": "",
                "en_name": "",
                "id": "",
                "image_url": "",
                "name": "",
                "operation_time": "",
                "tags": null,
                "telephone": "",
                "text": "",
                "type": {
                    "id": "",
                    "name": ""
                }
            },
            "add_info": null,
            "sid": 12804181
        },
        {
            "id": 10449,
            "thumbnail": "https://image.brandi.me/cproduct/2020/02/14/12161982_1581666374_image1_M.jpg",
            "name": "[Mnhoe] Creamy Tint Color Balm Intense 2.5G + [Ceramide Softener 25ml + Emuls 25ml quà tặng thêm]",
            "sale_price": 6300,
            "sale_percent": 30,
            "purchase_count": 1857,
            "price": 9000,
            "productEtcInfo": {},
            "seller": {
                "address1": "",
                "address2": "",
                "bookmark_count": 0,
                "business_info": {
                    "business_code": "",
                    "business_name": "",
                    "mail_order_business_code": "",
                    "representative_name": ""
                },
                "email": "",
                "en_name": "",
                "id": "",
                "image_url": "",
                "name": "",
                "operation_time": "",
                "tags": null,
                "telephone": "",
                "text": "",
                "type": {
                    "id": "",
                    "name": ""
                }
            },
            "add_info": null,
            "sid": 12161982
        },
        {
            "id": 11058,
            "thumbnail": "https://image.brandi.me/cproduct/2020/01/15/7139883_1579079313_image1_M.jpg",
            "name": "Son môi Rom & Zero Matt 13 màu",
            "sale_price": 6900,
            "sale_percent": 54,
            "purchase_count": 9967,
            "price": 15000,
            "productEtcInfo": {},
            "seller": {
                "address1": "",
                "address2": "",
                "bookmark_count": 0,
                "business_info": {
                    "business_code": "",
                    "business_name": "",
                    "mail_order_business_code": "",
                    "representative_name": ""
                },
                "email": "",
                "en_name": "",
                "id": "",
                "image_url": "",
                "name": "",
                "operation_time": "",
                "tags": null,
                "telephone": "",
                "text": "",
                "type": {
                    "id": "",
                    "name": ""
                }
            },
            "add_info": null,
            "sid": 7139883
        },
        {
            "id": 10476,
            "thumbnail": "https://image.brandi.me/cproduct/2019/12/20/12743834_1576825624_image1_M.jpg",
            "name": "Phấn má hồng",
            "sale_price": 8000,
            "sale_percent": 50,
            "purchase_count": 62,
            "price": 16000,
            "productEtcInfo": {},
            "seller": {
                "address1": "",
                "address2": "",
                "bookmark_count": 0,
                "business_info": {
                    "business_code": "",
                    "business_name": "",
                    "mail_order_business_code": "",
                    "representative_name": ""
                },
                "email": "",
                "en_name": "",
                "id": "",
                "image_url": "",
                "name": "",
                "operation_time": "",
                "tags": null,
                "telephone": "",
                "text": "",
                "type": {
                    "id": "",
                    "name": ""
                }
            },
            "add_info": null,
            "sid": 12743834
        },
        {
            "id": 10475,
            "thumbnail": "https://image.brandi.me/cproduct/2020/02/14/13816652_1581666547_image1_M.jpg",
            "name": "Tiến sĩ Mascara Fixer Perfect Trash 2ea",
            "sale_price": 8400,
            "sale_percent": 30,
            "purchase_count": 647,
            "price": 12000,
            "productEtcInfo": {},
            "seller": {
                "address1": "",
                "address2": "",
                "bookmark_count": 0,
                "business_info": {
                    "business_code": "",
                    "business_name": "",
                    "mail_order_business_code": "",
                    "representative_name": ""
                },
                "email": "",
                "en_name": "",
                "id": "",
                "image_url": "",
                "name": "",
                "operation_time": "",
                "tags": null,
                "telephone": "",
                "text": "",
                "type": {
                    "id": "",
                    "name": ""
                }
            },
            "add_info": null,
            "sid": 13816652
        },
        {
            "id": 10451,
            "thumbnail": "https://image.brandi.me/cproduct/2020/01/23/11601775_1579748379_image1_M.jpg",
            "name": "Tâm trạng Liar Velvet Tint",
            "sale_price": 8500,
            "sale_percent": 15,
            "purchase_count": 3015,
            "price": 10000,
            "productEtcInfo": {},
            "seller": {
                "address1": "",
                "address2": "",
                "bookmark_count": 0,
                "business_info": {
                    "business_code": "",
                    "business_name": "",
                    "mail_order_business_code": "",
                    "representative_name": ""
                },
                "email": "",
                "en_name": "",
                "id": "",
                "image_url": "",
                "name": "",
                "operation_time": "",
                "tags": null,
                "telephone": "",
                "text": "",
                "type": {
                    "id": "",
                    "name": ""
                }
            },
            "add_info": null,
            "sid": 11601775
        },
        {
            "id": 10470,
            "thumbnail": "https://image.brandi.me/cproduct/2019/12/23/12549129_1577068951_image1_M.jpg",
            "name": "Rome và vũ trụ Liquid long lanh 4 màu",
            "sale_price": 8880,
            "sale_percent": 26,
            "purchase_count": 910,
            "price": 12000,
            "productEtcInfo": {},
            "seller": {
                "address1": "",
                "address2": "",
                "bookmark_count": 0,
                "business_info": {
                    "business_code": "",
                    "business_name": "",
                    "mail_order_business_code": "",
                    "representative_name": ""
                },
                "email": "",
                "en_name": "",
                "id": "",
                "image_url": "",
                "name": "",
                "operation_time": "",
                "tags": null,
                "telephone": "",
                "text": "",
                "type": {
                    "id": "",
                    "name": ""
                }
            },
            "add_info": null,
            "sid": 12549129
        },
        {
            "id": 10458,
            "thumbnail": "https://image.brandi.me/cproduct/2020/04/02/15127713_1585794667_image1_M.jpg",
            "name": "[Tôi là Mimi] Mystery Blur Tint",
            "sale_price": 8880,
            "sale_percent": 26,
            "purchase_count": 29,
            "price": 12000,
            "productEtcInfo": {},
            "seller": {
                "address1": "",
                "address2": "",
                "bookmark_count": 0,
                "business_info": {
                    "business_code": "",
                    "business_name": "",
                    "mail_order_business_code": "",
                    "representative_name": ""
                },
                "email": "",
                "en_name": "",
                "id": "",
                "image_url": "",
                "name": "",
                "operation_time": "",
                "tags": null,
                "telephone": "",
                "text": "",
                "type": {
                    "id": "",
                    "name": ""
                }
            },
            "add_info": null,
            "sid": 15127713
        },
        {
            "id": 10442,
            "thumbnail": "https://image.brandi.me/cproduct/2020/03/31/14975037_1585625592_image1_M.jpg",
            "name": "[Quà tặng] The Saem Single Blizer + Tip Che khuyết điểm + Cọ (Quà tặng)",
            "sale_price": 9000,
            "sale_percent": 10,
            "purchase_count": 199,
            "price": 10000,
            "productEtcInfo": {},
            "seller": {
                "address1": "",
                "address2": "",
                "bookmark_count": 0,
                "business_info": {
                    "business_code": "",
                    "business_name": "",
                    "mail_order_business_code": "",
                    "representative_name": ""
                },
                "email": "",
                "en_name": "",
                "id": "",
                "image_url": "",
                "name": "",
                "operation_time": "",
                "tags": null,
                "telephone": "",
                "text": "",
                "type": {
                    "id": "",
                    "name": ""
                }
            },
            "add_info": null,
            "sid": 14975037
        },
        {
            "id": 10448,
            "thumbnail": "https://image.brandi.me/cproduct/2020/04/06/15157853_1586148090_image1_M.jpg",
            "name": "Barer Dan Cheek Sữa Series 3 màu",
            "sale_price": 9000,
            "sale_percent": 25,
            "purchase_count": 129,
            "price": 12000,
            "productEtcInfo": {},
            "seller": {
                "address1": "",
                "address2": "",
                "bookmark_count": 0,
                "business_info": {
                    "business_code": "",
                    "business_name": "",
                    "mail_order_business_code": "",
                    "representative_name": ""
                },
                "email": "",
                "en_name": "",
                "id": "",
                "image_url": "",
                "name": "",
                "operation_time": "",
                "tags": null,
                "telephone": "",
                "text": "",
                "type": {
                    "id": "",
                    "name": ""
                }
            },
            "add_info": null,
            "sid": 15157853
        },
        {
            "id": 10444,
            "thumbnail": "https://image.brandi.me/cproduct/2020/04/17/13387578_1587102884_image1_M.jpg",
            "name": "(Air-Fit Lipstick Present) Lyr Six Eye Palette / 6 Color Shadow Palette",
            "sale_price": 9000,
            "sale_percent": 64,
            "purchase_count": 325,
            "price": 25000,
            "productEtcInfo": {},
            "seller": {
                "address1": "",
                "address2": "",
                "bookmark_count": 0,
                "business_info": {
                    "business_code": "",
                    "business_name": "",
                    "mail_order_business_code": "",
                    "representative_name": ""
                },
                "email": "",
                "en_name": "",
                "id": "",
                "image_url": "",
                "name": "",
                "operation_time": "",
                "tags": null,
                "telephone": "",
                "text": "",
                "type": {
                    "id": "",
                    "name": ""
                }
            },
            "add_info": null,
            "sid": 13387578
        },
        {
            "id": 10464,
            "thumbnail": "https://image.brandi.me/cproduct/2020/04/13/15412797_1586765235_image1_M.jpg",
            "name": "[Labelyoung] Shocking Body Bar Calming Version Xà phòng làm bằng tay",
            "sale_price": 9750,
            "sale_percent": 35,
            "price": 15000,
            "productEtcInfo": {},
            "seller": {
                "address1": "",
                "address2": "",
                "bookmark_count": 0,
                "business_info": {
                    "business_code": "",
                    "business_name": "",
                    "mail_order_business_code": "",
                    "representative_name": ""
                },
                "email": "",
                "en_name": "",
                "id": "",
                "image_url": "",
                "name": "",
                "operation_time": "",
                "tags": null,
                "telephone": "",
                "text": "",
                "type": {
                    "id": "",
                    "name": ""
                }
            },
            "add_info": null,
            "sid": 15412797
        },
        {
            "id": 10459,
            "thumbnail": "https://image.brandi.me/cproduct/2020/04/13/14589709_1586761033_image1_M.jpg",
            "name": "[Vodana] Dừng lại với Godae Godae Iron Fixer 100ml",
            "sale_price": 9860,
            "sale_percent": 42,
            "purchase_count": 51,
            "price": 17000,
            "productEtcInfo": {},
            "seller": {
                "address1": "",
                "address2": "",
                "bookmark_count": 0,
                "business_info": {
                    "business_code": "",
                    "business_name": "",
                    "mail_order_business_code": "",
                    "representative_name": ""
                },
                "email": "",
                "en_name": "",
                "id": "",
                "image_url": "",
                "name": "",
                "operation_time": "",
                "tags": null,
                "telephone": "",
                "text": "",
                "type": {
                    "id": "",
                    "name": ""
                }
            },
            "add_info": null,
            "sid": 14589709
        },
        {
            "id": 6054,
            "thumbnail": "https://image.brandi.me/cproduct/2020/04/01/15094390_1585703415_image1_L.jpg",
            "name": "Romatic color and Glampalm",
            "sale_price": 9880,
            "sale_percent": 24,
            "purchase_count": 196,
            "price": 13000,
            "productEtcInfo": {},
            "seller": {
                "address1": "",
                "address2": "",
                "bookmark_count": 0,
                "business_info": {
                    "business_code": "",
                    "business_name": "",
                    "mail_order_business_code": "",
                    "representative_name": ""
                },
                "email": "",
                "en_name": "",
                "id": "",
                "image_url": "",
                "name": "",
                "operation_time": "",
                "tags": null,
                "telephone": "",
                "text": "",
                "type": {
                    "id": "",
                    "name": ""
                }
            },
            "add_info": null,
            "sid": 15094390
        },
        {
            "id": 10461,
            "thumbnail": "https://image.brandi.me/cproduct/2020/01/15/7139940_1579079326_image1_M.jpg",
            "name": "Rom & Zero Velvet 11 màu",
            "sale_price": 9880,
            "sale_percent": 24,
            "purchase_count": 9823,
            "price": 13000,
            "productEtcInfo": {},
            "seller": {
                "address1": "",
                "address2": "",
                "bookmark_count": 0,
                "business_info": {
                    "business_code": "",
                    "business_name": "",
                    "mail_order_business_code": "",
                    "representative_name": ""
                },
                "email": "",
                "en_name": "",
                "id": "",
                "image_url": "",
                "name": "",
                "operation_time": "",
                "tags": null,
                "telephone": "",
                "text": "",
                "type": {
                    "id": "",
                    "name": ""
                }
            },
            "add_info": null,
            "sid": 7139940
        },
        {
            "id": 11054,
            "thumbnail": "https://image.brandi.me/cproduct/2020/03/06/14301055_1583460045_image1_M.jpg",
            "name": "Chơi màu Mắt trái tim nở",
            "sale_price": 9900,
            "sale_percent": 45,
            "purchase_count": 717,
            "price": 18000,
            "productEtcInfo": {},
            "seller": {
                "address1": "",
                "address2": "",
                "bookmark_count": 0,
                "business_info": {
                    "business_code": "",
                    "business_name": "",
                    "mail_order_business_code": "",
                    "representative_name": ""
                },
                "email": "",
                "en_name": "",
                "id": "",
                "image_url": "",
                "name": "",
                "operation_time": "",
                "tags": null,
                "telephone": "",
                "text": "",
                "type": {
                    "id": "",
                    "name": ""
                }
            },
            "add_info": null,
            "sid": 14301055
        },
        {
            "id": 11057,
            "thumbnail": "https://image.brandi.me/cproduct/2019/09/25/8623933_1569402156_image1_M.jpg",
            "name": "[1 + 1] Sương mù cơ thể",
            "sale_price": 10000,
            "sale_percent": 50,
            "purchase_count": 1398,
            "price": 20000,
            "productEtcInfo": {},
            "seller": {
                "address1": "",
                "address2": "",
                "bookmark_count": 0,
                "business_info": {
                    "business_code": "",
                    "business_name": "",
                    "mail_order_business_code": "",
                    "representative_name": ""
                },
                "email": "",
                "en_name": "",
                "id": "",
                "image_url": "",
                "name": "",
                "operation_time": "",
                "tags": null,
                "telephone": "",
                "text": "",
                "type": {
                    "id": "",
                    "name": ""
                }
            },
            "add_info": null,
            "sid": 8623933
        },
        {
            "id": 10469,
            "thumbnail": "https://image.brandi.me/cproduct/2020/04/13/14760597_1586770841_image1_M.jpg",
            "name": "[Flin] 6 loại màu phủ ảo giác",
            "sale_price": 10050,
            "sale_percent": 33,
            "purchase_count": 40,
            "price": 15000,
            "productEtcInfo": {},
            "seller": {
                "address1": "",
                "address2": "",
                "bookmark_count": 0,
                "business_info": {
                    "business_code": "",
                    "business_name": "",
                    "mail_order_business_code": "",
                    "representative_name": ""
                },
                "email": "",
                "en_name": "",
                "id": "",
                "image_url": "",
                "name": "",
                "operation_time": "",
                "tags": null,
                "telephone": "",
                "text": "",
                "type": {
                    "id": "",
                    "name": ""
                }
            },
            "add_info": null,
            "sid": 14760597
        },
        {
            "id": 10447,
            "thumbnail": "https://image.brandi.me/cproduct/2020/04/17/9594298_1587091424_image1_M.jpg",
            "name": "(Trình bày cọ mặt) Tạo bóng ba màu / Trang điểm 3 màu",
            "sale_price": 10150,
            "sale_percent": 71,
            "purchase_count": 4717,
            "price": 35000,
            "productEtcInfo": {},
            "seller": {
                "address1": "",
                "address2": "",
                "bookmark_count": 0,
                "business_info": {
                    "business_code": "",
                    "business_name": "",
                    "mail_order_business_code": "",
                    "representative_name": ""
                },
                "email": "",
                "en_name": "",
                "id": "",
                "image_url": "",
                "name": "",
                "operation_time": "",
                "tags": null,
                "telephone": "",
                "text": "",
                "type": {
                    "id": "",
                    "name": ""
                }
            },
            "add_info": null,
            "sid": 9594298
        },
        {
            "id": 10443,
            "thumbnail": "https://image.brandi.me/cproduct/2020/04/02/14534069_1585788922_image1_M.jpg",
            "name": "[Bộ sưu tập Flash Pulley] Bảng màu mắt 4",
            "sale_price": 10500,
            "sale_percent": 30,
            "purchase_count": 173,
            "price": 15000,
            "productEtcInfo": {},
            "seller": {
                "address1": "",
                "address2": "",
                "bookmark_count": 0,
                "business_info": {
                    "business_code": "",
                    "business_name": "",
                    "mail_order_business_code": "",
                    "representative_name": ""
                },
                "email": "",
                "en_name": "",
                "id": "",
                "image_url": "",
                "name": "",
                "operation_time": "",
                "tags": null,
                "telephone": "",
                "text": "",
                "type": {
                    "id": "",
                    "name": ""
                }
            },
            "add_info": null,
            "sid": 14534069
        },
        {
            "id": 10467,
            "thumbnail": "https://image.brandi.me/cproduct/2020/01/15/9889892_1579079856_image1_M.jpg",
            "name": "Rom & See Through Matte Tint 6color",
            "sale_price": 10920,
            "sale_percent": 16,
            "purchase_count": 3589,
            "price": 13000,
            "productEtcInfo": {},
            "seller": {
                "address1": "",
                "address2": "",
                "bookmark_count": 0,
                "business_info": {
                    "business_code": "",
                    "business_name": "",
                    "mail_order_business_code": "",
                    "representative_name": ""
                },
                "email": "",
                "en_name": "",
                "id": "",
                "image_url": "",
                "name": "",
                "operation_time": "",
                "tags": null,
                "telephone": "",
                "text": "",
                "type": {
                    "id": "",
                    "name": ""
                }
            },
            "add_info": null,
            "sid": 9889892
        },
        {
            "id": 10466,
            "thumbnail": "https://image.brandi.me/cproduct/2020/01/15/10466528_1579079878_image1_M.jpg",
            "name": "Son môi Rome & Zero Layer 6 màu",
            "sale_price": 10950,
            "sale_percent": 27,
            "purchase_count": 1668,
            "price": 15000,
            "productEtcInfo": {},
            "seller": {
                "address1": "",
                "address2": "",
                "bookmark_count": 0,
                "business_info": {
                    "business_code": "",
                    "business_name": "",
                    "mail_order_business_code": "",
                    "representative_name": ""
                },
                "email": "",
                "en_name": "",
                "id": "",
                "image_url": "",
                "name": "",
                "operation_time": "",
                "tags": null,
                "telephone": "",
                "text": "",
                "type": {
                    "id": "",
                    "name": ""
                }
            },
            "add_info": null,
            "sid": 10466528
        },
        {
            "id": 11062,
            "thumbnail": "https://image.brandi.me/cproduct/2020/04/23/7409804_1587627696_image1_M.jpg",
            "name": "[1 + 1 + Quà tặng] 3 loại bút kẻ mắt hợp nhất (2 chiếc) + son môi miễn phí (L16)!",
            "sale_price": 11350,
            "sale_percent": 50,
            "purchase_count": 33137,
            "price": 22700,
            "productEtcInfo": {},
            "seller": {
                "address1": "",
                "address2": "",
                "bookmark_count": 0,
                "business_info": {
                    "business_code": "",
                    "business_name": "",
                    "mail_order_business_code": "",
                    "representative_name": ""
                },
                "email": "",
                "en_name": "",
                "id": "",
                "image_url": "",
                "name": "",
                "operation_time": "",
                "tags": null,
                "telephone": "",
                "text": "",
                "type": {
                    "id": "",
                    "name": ""
                }
            },
            "add_info": null,
            "sid": 7409804
        },
        {
            "id": 6096,
            "thumbnail": "https://image.brandi.me/cproduct/2020/02/10/7992275_1581297239_image1_L.jpg",
            "name": "Son tint của máy bay màu đen",
            "sale_price": 12516,
            "sale_percent": 58,
            "purchase_count": 1383,
            "price": 29800,
            "productEtcInfo": {},
            "seller": {
                "address1": "",
                "address2": "",
                "bookmark_count": 0,
                "business_info": {
                    "business_code": "",
                    "business_name": "",
                    "mail_order_business_code": "",
                    "representative_name": ""
                },
                "email": "",
                "en_name": "",
                "id": "",
                "image_url": "",
                "name": "",
                "operation_time": "",
                "tags": null,
                "telephone": "",
                "text": "",
                "type": {
                    "id": "",
                    "name": ""
                }
            },
            "add_info": null,
            "sid": 7992275
        },
        {
            "id": 10471,
            "thumbnail": "https://image.brandi.me/cproduct/2020/04/01/15098389_1585710205_image1_M.jpg",
            "name": "MÀU SẮC CỦA TÔI CHEEK LOG-6",
            "sale_price": 12600,
            "sale_percent": 10,
            "purchase_count": 92,
            "price": 14000,
            "productEtcInfo": {},
            "seller": {
                "address1": "",
                "address2": "",
                "bookmark_count": 0,
                "business_info": {
                    "business_code": "",
                    "business_name": "",
                    "mail_order_business_code": "",
                    "representative_name": ""
                },
                "email": "",
                "en_name": "",
                "id": "",
                "image_url": "",
                "name": "",
                "operation_time": "",
                "tags": null,
                "telephone": "",
                "text": "",
                "type": {
                    "id": "",
                    "name": ""
                }
            },
            "add_info": null,
            "sid": 15098389
        },
        {
            "id": 10446,
            "thumbnail": "https://image.brandi.me/cproduct/2020/04/02/15143628_1585808165_image1_M.jpg",
            "name": "[Hiệu ứng Pony] Powder Touch Lip Color",
            "sale_price": 12600,
            "sale_percent": 30,
            "purchase_count": 66,
            "price": 18000,
            "productEtcInfo": {},
            "seller": {
                "address1": "",
                "address2": "",
                "bookmark_count": 0,
                "business_info": {
                    "business_code": "",
                    "business_name": "",
                    "mail_order_business_code": "",
                    "representative_name": ""
                },
                "email": "",
                "en_name": "",
                "id": "",
                "image_url": "",
                "name": "",
                "operation_time": "",
                "tags": null,
                "telephone": "",
                "text": "",
                "type": {
                    "id": "",
                    "name": ""
                }
            },
            "add_info": null,
            "sid": 15143628
        },
        {
            "id": 10455,
            "thumbnail": "https://image.brandi.me/cproduct/2020/02/20/13781232_1582177418_image1_M.jpg",
            "name": "ETUDE Double Lasting Foundation",
            "sale_price": 12600,
            "sale_percent": 30,
            "purchase_count": 518,
            "price": 18000,
            "productEtcInfo": {},
            "seller": {
                "address1": "",
                "address2": "",
                "bookmark_count": 0,
                "business_info": {
                    "business_code": "",
                    "business_name": "",
                    "mail_order_business_code": "",
                    "representative_name": ""
                },
                "email": "",
                "en_name": "",
                "id": "",
                "image_url": "",
                "name": "",
                "operation_time": "",
                "tags": null,
                "telephone": "",
                "text": "",
                "type": {
                    "id": "",
                    "name": ""
                }
            },
            "add_info": null,
            "sid": 13781232
        },
        {
            "id": 11059,
            "thumbnail": "https://image.brandi.me/cproduct/2019/11/08/11139467_1573193131_image1_M.jpg",
            "name": "[Mnhoe] [1 + 1] Creamy Tint Color Balm Intense 2.5G",
            "sale_price": 12600,
            "sale_percent": 30,
            "purchase_count": 869,
            "price": 18000,
            "productEtcInfo": {},
            "seller": {
                "address1": "",
                "address2": "",
                "bookmark_count": 0,
                "business_info": {
                    "business_code": "",
                    "business_name": "",
                    "mail_order_business_code": "",
                    "representative_name": ""
                },
                "email": "",
                "en_name": "",
                "id": "",
                "image_url": "",
                "name": "",
                "operation_time": "",
                "tags": null,
                "telephone": "",
                "text": "",
                "type": {
                    "id": "",
                    "name": ""
                }
            },
            "add_info": null,
            "sid": 11139467
        },
        {
            "id": 6124,
            "thumbnail": "https://image.brandi.me/cproduct/2020/03/18/14692996_1584509457_image1_L.jpg",
            "name": "chì phẳng",
            "sale_price": 13500,
            "sale_percent": 25,
            "purchase_count": 62,
            "price": 18000,
            "productEtcInfo": {},
            "seller": {
                "address1": "",
                "address2": "",
                "bookmark_count": 0,
                "business_info": {
                    "business_code": "",
                    "business_name": "",
                    "mail_order_business_code": "",
                    "representative_name": ""
                },
                "email": "",
                "en_name": "",
                "id": "",
                "image_url": "",
                "name": "",
                "operation_time": "",
                "tags": null,
                "telephone": "",
                "text": "",
                "type": {
                    "id": "",
                    "name": ""
                }
            },
            "add_info": null,
            "sid": 14692996
        },
        {
            "id": 11601,
            "thumbnail": "https://image.brandi.me/cproduct/2020/04/17/15580116_1587105209_image1_M.jpg",
            "name": "[1 + 1] Son môi Rom & Zero Layer 6 màu",
            "sale_price": 14190,
            "sale_percent": 57,
            "purchase_count": 192,
            "price": 33000,
            "productEtcInfo": {},
            "seller": {
                "address1": "",
                "address2": "",
                "bookmark_count": 0,
                "business_info": {
                    "business_code": "",
                    "business_name": "",
                    "mail_order_business_code": "",
                    "representative_name": ""
                },
                "email": "",
                "en_name": "",
                "id": "",
                "image_url": "",
                "name": "",
                "operation_time": "",
                "tags": null,
                "telephone": "",
                "text": "",
                "type": {
                    "id": "",
                    "name": ""
                }
            },
            "add_info": null,
            "sid": 15580116
        },
        {
            "id": 10473,
            "thumbnail": "https://image.brandi.me/cproduct/2020/03/25/12890697_1585109587_image1_M.jpg",
            "name": "[Laneige] Mặt nạ ngủ 20g (tùy chọn) + [Mặt nạ ngủ Berry Berry 3g x 3 phụ]",
            "sale_price": 14400,
            "sale_percent": 20,
            "purchase_count": 603,
            "price": 18000,
            "productEtcInfo": {},
            "seller": {
                "address1": "",
                "address2": "",
                "bookmark_count": 0,
                "business_info": {
                    "business_code": "",
                    "business_name": "",
                    "mail_order_business_code": "",
                    "representative_name": ""
                },
                "email": "",
                "en_name": "",
                "id": "",
                "image_url": "",
                "name": "",
                "operation_time": "",
                "tags": null,
                "telephone": "",
                "text": "",
                "type": {
                    "id": "",
                    "name": ""
                }
            },
            "add_info": null,
            "sid": 12890697
        },
        {
            "id": 10457,
            "thumbnail": "https://image.brandi.me/cproduct/2020/04/10/15407374_1586506299_image1_M.jpg",
            "name": "Son dưỡng môi sóng long lanh",
            "sale_price": 14630,
            "sale_percent": 5,
            "price": 15400,
            "productEtcInfo": {},
            "seller": {
                "address1": "",
                "address2": "",
                "bookmark_count": 0,
                "business_info": {
                    "business_code": "",
                    "business_name": "",
                    "mail_order_business_code": "",
                    "representative_name": ""
                },
                "email": "",
                "en_name": "",
                "id": "",
                "image_url": "",
                "name": "",
                "operation_time": "",
                "tags": null,
                "telephone": "",
                "text": "",
                "type": {
                    "id": "",
                    "name": ""
                }
            },
            "add_info": null,
            "sid": 15407374
        },
        {
            "id": 11053,
            "thumbnail": "https://image.brandi.me/cproduct/2020/03/20/14769532_1584692952_image1_M.jpg",
            "name": "1001 tông màu trên bảng màu tông màu Chế độ nâu PRO9",
            "sale_price": 14820,
            "sale_percent": 62,
            "purchase_count": 462,
            "price": 39000,
            "productEtcInfo": {},
            "seller": {
                "address1": "",
                "address2": "",
                "bookmark_count": 0,
                "business_info": {
                    "business_code": "",
                    "business_name": "",
                    "mail_order_business_code": "",
                    "representative_name": ""
                },
                "email": "",
                "en_name": "",
                "id": "",
                "image_url": "",
                "name": "",
                "operation_time": "",
                "tags": null,
                "telephone": "",
                "text": "",
                "type": {
                    "id": "",
                    "name": ""
                }
            },
            "add_info": null,
            "sid": 14769532
        },
        {
            "id": 6119,
            "thumbnail": "https://image.brandi.me/cproduct/2020/02/25/14067282_1582608337_image1_L.jpg",
            "name": "[Mnhoe] Creamy Tint Color Balm Intense Mini 3 Bộ đặc biệt",
            "sale_price": 14940,
            "sale_percent": 17,
            "purchase_count": 203,
            "price": 18000,
            "productEtcInfo": {},
            "seller": {
                "address1": "",
                "address2": "",
                "bookmark_count": 0,
                "business_info": {
                    "business_code": "",
                    "business_name": "",
                    "mail_order_business_code": "",
                    "representative_name": ""
                },
                "email": "",
                "en_name": "",
                "id": "",
                "image_url": "",
                "name": "",
                "operation_time": "",
                "tags": null,
                "telephone": "",
                "text": "",
                "type": {
                    "id": "",
                    "name": ""
                }
            },
            "add_info": null,
            "sid": 14067282
        },
        {
            "id": 11055,
            "thumbnail": "https://image.brandi.me/cproduct/2020/03/06/14343432_1583472960_image1_M.jpg",
            "name": "Chơi màu mắt",
            "sale_price": 15400,
            "sale_percent": 30,
            "purchase_count": 928,
            "price": 22000,
            "productEtcInfo": {},
            "seller": {
                "address1": "",
                "address2": "",
                "bookmark_count": 0,
                "business_info": {
                    "business_code": "",
                    "business_name": "",
                    "mail_order_business_code": "",
                    "representative_name": ""
                },
                "email": "",
                "en_name": "",
                "id": "",
                "image_url": "",
                "name": "",
                "operation_time": "",
                "tags": null,
                "telephone": "",
                "text": "",
                "type": {
                    "id": "",
                    "name": ""
                }
            },
            "add_info": null,
            "sid": 14343432
        },
        {
            "id": 11061,
            "thumbnail": "https://image.brandi.me/cproduct/2020/03/06/8160338_1583465388_image1_M.jpg",
            "name": "[Giá đặc biệt] Kem Centurion Cica 50ml",
            "sale_price": 15660,
            "sale_percent": 73,
            "purchase_count": 969,
            "price": 58000,
            "productEtcInfo": {},
            "seller": {
                "address1": "",
                "address2": "",
                "bookmark_count": 0,
                "business_info": {
                    "business_code": "",
                    "business_name": "",
                    "mail_order_business_code": "",
                    "representative_name": ""
                },
                "email": "",
                "en_name": "",
                "id": "",
                "image_url": "",
                "name": "",
                "operation_time": "",
                "tags": null,
                "telephone": "",
                "text": "",
                "type": {
                    "id": "",
                    "name": ""
                }
            },
            "add_info": null,
            "sid": 8160338
        },
        {
            "id": 6104,
            "thumbnail": "https://image.brandi.me/cproduct/2020/02/10/10109442_1581296901_image1_L.jpg",
            "name": "[Độc quyền] Air Fit Velvet 4+ Air Fit Velvet 2",
            "sale_price": 15794,
            "sale_percent": 47,
            "purchase_count": 1435,
            "price": 29800,
            "productEtcInfo": {},
            "seller": {
                "address1": "",
                "address2": "",
                "bookmark_count": 0,
                "business_info": {
                    "business_code": "",
                    "business_name": "",
                    "mail_order_business_code": "",
                    "representative_name": ""
                },
                "email": "",
                "en_name": "",
                "id": "",
                "image_url": "",
                "name": "",
                "operation_time": "",
                "tags": null,
                "telephone": "",
                "text": "",
                "type": {
                    "id": "",
                    "name": ""
                }
            },
            "add_info": null,
            "sid": 10109442
        },
        {
            "id": 10474,
            "thumbnail": "https://image.brandi.me/cproduct/2019/10/04/7581750_1570165935_image1_M.jpg",
            "name": "Ella Portable Mini Curling Iron MMS-8224",
            "sale_price": 15920,
            "sale_percent": 20,
            "purchase_count": 2408,
            "price": 19900,
            "productEtcInfo": {},
            "seller": {
                "address1": "",
                "address2": "",
                "bookmark_count": 0,
                "business_info": {
                    "business_code": "",
                    "business_name": "",
                    "mail_order_business_code": "",
                    "representative_name": ""
                },
                "email": "",
                "en_name": "",
                "id": "",
                "image_url": "",
                "name": "",
                "operation_time": "",
                "tags": null,
                "telephone": "",
                "text": "",
                "type": {
                    "id": "",
                    "name": ""
                }
            },
            "add_info": null,
            "sid": 7581750
        },
        {
            "id": 11060,
            "thumbnail": "https://image.brandi.me/cproduct/2020/01/15/8904270_1579079845_image1_M.jpg",
            "name": "Mắt Rom & Vero Dan 6 màu",
            "sale_price": 16020,
            "sale_percent": 11,
            "purchase_count": 7684,
            "price": 18000,
            "productEtcInfo": {},
            "seller": {
                "address1": "",
                "address2": "",
                "bookmark_count": 0,
                "business_info": {
                    "business_code": "",
                    "business_name": "",
                    "mail_order_business_code": "",
                    "representative_name": ""
                },
                "email": "",
                "en_name": "",
                "id": "",
                "image_url": "",
                "name": "",
                "operation_time": "",
                "tags": null,
                "telephone": "",
                "text": "",
                "type": {
                    "id": "",
                    "name": ""
                }
            },
            "add_info": null,
            "sid": 8904270
        },
        {
            "id": 11411,
            "thumbnail": "https://image.brandi.me/cproduct/2020/04/17/15579224_1587103885_image1_M.jpg",
            "name": "[1 + 1] Rom & Zero Velvet Tint 11color + Ví thẻ Cơ sở đến trước được phục vụ trước",
            "sale_price": 16900,
            "sale_percent": 35,
            "purchase_count": 88,
            "price": 26000,
            "productEtcInfo": {},
            "seller": {
                "address1": "",
                "address2": "",
                "bookmark_count": 0,
                "business_info": {
                    "business_code": "",
                    "business_name": "",
                    "mail_order_business_code": "",
                    "representative_name": ""
                },
                "email": "",
                "en_name": "",
                "id": "",
                "image_url": "",
                "name": "",
                "operation_time": "",
                "tags": null,
                "telephone": "",
                "text": "",
                "type": {
                    "id": "",
                    "name": ""
                }
            },
            "add_info": null,
            "sid": 15579224
        },
        {
            "id": 11403,
            "thumbnail": "https://image.brandi.me/cproduct/2020/04/21/15663715_1587434035_image1_M.jpg",
            "name": "Bộ dụng cụ chọn mùa xuân (bóng 1, má hồng 1, son 1)",
            "sale_price": 18400,
            "sale_percent": 60,
            "purchase_count": 40,
            "price": 46000,
            "productEtcInfo": {},
            "seller": {
                "address1": "",
                "address2": "",
                "bookmark_count": 0,
                "business_info": {
                    "business_code": "",
                    "business_name": "",
                    "mail_order_business_code": "",
                    "representative_name": ""
                },
                "email": "",
                "en_name": "",
                "id": "",
                "image_url": "",
                "name": "",
                "operation_time": "",
                "tags": null,
                "telephone": "",
                "text": "",
                "type": {
                    "id": "",
                    "name": ""
                }
            },
            "add_info": null,
            "sid": 15663715
        },
        {
            "id": 6123,
            "thumbnail": "https://image.brandi.me/cproduct/2020/02/10/13687001_1581320707_image1_L.jpg",
            "name": "[Tueen] Lip Magnet (5 màu)",
            "sale_price": 18700,
            "price": 18700,
            "productEtcInfo": {},
            "seller": {
                "address1": "",
                "address2": "",
                "bookmark_count": 0,
                "business_info": {
                    "business_code": "",
                    "business_name": "",
                    "mail_order_business_code": "",
                    "representative_name": ""
                },
                "email": "",
                "en_name": "",
                "id": "",
                "image_url": "",
                "name": "",
                "operation_time": "",
                "tags": null,
                "telephone": "",
                "text": "",
                "type": {
                    "id": "",
                    "name": ""
                }
            },
            "add_info": null,
            "sid": 13687001
        },
        {
            "id": 10452,
            "thumbnail": "https://image.brandi.me/cproduct/2020/02/05/9875015_1580867572_image1_M.jpg",
            "name": "Lấy gel long lanh",
            "sale_price": 18810,
            "sale_percent": 5,
            "purchase_count": 1720,
            "price": 19800,
            "productEtcInfo": {},
            "seller": {
                "address1": "",
                "address2": "",
                "bookmark_count": 0,
                "business_info": {
                    "business_code": "",
                    "business_name": "",
                    "mail_order_business_code": "",
                    "representative_name": ""
                },
                "email": "",
                "en_name": "",
                "id": "",
                "image_url": "",
                "name": "",
                "operation_time": "",
                "tags": null,
                "telephone": "",
                "text": "",
                "type": {
                    "id": "",
                    "name": ""
                }
            },
            "add_info": null,
            "sid": 9875015
        },
        {
            "id": 10445,
            "thumbnail": "https://image.brandi.me/cproduct/2020/02/14/13450397_1581658938_image1_M.jpg",
            "name": "[Giá đặc biệt] [McQueen New York_MQNY] Bộ dụng cụ lông mi",
            "sale_price": 18900,
            "sale_percent": 65,
            "purchase_count": 307,
            "price": 54000,
            "productEtcInfo": {},
            "seller": {
                "address1": "",
                "address2": "",
                "bookmark_count": 0,
                "business_info": {
                    "business_code": "",
                    "business_name": "",
                    "mail_order_business_code": "",
                    "representative_name": ""
                },
                "email": "",
                "en_name": "",
                "id": "",
                "image_url": "",
                "name": "",
                "operation_time": "",
                "tags": null,
                "telephone": "",
                "text": "",
                "type": {
                    "id": "",
                    "name": ""
                }
            },
            "add_info": null,
            "sid": 13450397
        },
        {
            "id": 6122,
            "thumbnail": "https://image.brandi.me/cproduct/2020/03/30/11036009_1585533186_image1_L.jpg",
            "name": "[1 + 1] Hợp nhất Mellow Tint 8ea (2ea)",
            "sale_price": 19580,
            "purchase_count": 1376,
            "price": 19580,
            "productEtcInfo": {},
            "seller": {
                "address1": "",
                "address2": "",
                "bookmark_count": 0,
                "business_info": {
                    "business_code": "",
                    "business_name": "",
                    "mail_order_business_code": "",
                    "representative_name": ""
                },
                "email": "",
                "en_name": "",
                "id": "",
                "image_url": "",
                "name": "",
                "operation_time": "",
                "tags": null,
                "telephone": "",
                "text": "",
                "type": {
                    "id": "",
                    "name": ""
                }
            },
            "add_info": null,
            "sid": 11036009
        },
        {
            "id": 10468,
            "thumbnail": "https://image.brandi.me/cproduct/2020/01/29/13410852_1580273916_image1_M.jpg",
            "name": "[Hera] Black Cushion Refill 15g + [3 Cell Mask + 50ml Bọt rửa mặt + 15ml Nước tuổi + 15ml Nhũ tương Quà tặng thêm]",
            "sale_price": 21250,
            "sale_percent": 15,
            "purchase_count": 81,
            "price": 25000,
            "productEtcInfo": {},
            "seller": {
                "address1": "",
                "address2": "",
                "bookmark_count": 0,
                "business_info": {
                    "business_code": "",
                    "business_name": "",
                    "mail_order_business_code": "",
                    "representative_name": ""
                },
                "email": "",
                "en_name": "",
                "id": "",
                "image_url": "",
                "name": "",
                "operation_time": "",
                "tags": null,
                "telephone": "",
                "text": "",
                "type": {
                    "id": "",
                    "name": ""
                }
            },
            "add_info": null,
            "sid": 13410852
        },
        {
            "id": 10463,
            "thumbnail": "https://image.brandi.me/cproduct/2020/03/09/13409016_1583722410_image1_M.jpg",
            "name": "[1 + 1] Hợp nhất tông màu 8ea (2ea)",
            "sale_price": 21780,
            "purchase_count": 1735,
            "price": 21780,
            "productEtcInfo": {},
            "seller": {
                "address1": "",
                "address2": "",
                "bookmark_count": 0,
                "business_info": {
                    "business_code": "",
                    "business_name": "",
                    "mail_order_business_code": "",
                    "representative_name": ""
                },
                "email": "",
                "en_name": "",
                "id": "",
                "image_url": "",
                "name": "",
                "operation_time": "",
                "tags": null,
                "telephone": "",
                "text": "",
                "type": {
                    "id": "",
                    "name": ""
                }
            },
            "add_info": null,
            "sid": 13409016
        },
        {
            "id": 11056,
            "thumbnail": "https://image.brandi.me/cproduct/2020/03/02/9882698_1583116709_image1_M.jpg",
            "name": "[McQueen New York_MQNY] Bộ trang điểm mắt gồm 4 (tông màu trên bóng + bút ara + bút chì lông mày + cọ bóng)",
            "sale_price": 21898,
            "sale_percent": 67,
            "purchase_count": 8994,
            "price": 66360,
            "productEtcInfo": {},
            "seller": {
                "address1": "",
                "address2": "",
                "bookmark_count": 0,
                "business_info": {
                    "business_code": "",
                    "business_name": "",
                    "mail_order_business_code": "",
                    "representative_name": ""
                },
                "email": "",
                "en_name": "",
                "id": "",
                "image_url": "",
                "name": "",
                "operation_time": "",
                "tags": null,
                "telephone": "",
                "text": "",
                "type": {
                    "id": "",
                    "name": ""
                }
            },
            "add_info": null,
            "sid": 9882698
        },
        {
            "id": 6036,
            "thumbnail": "https://image.brandi.me/cproduct/2020/03/16/9819636_1584322848_image1_L.jpg",
            "name": "[Thuyết trình] [1 + 1] Lựa chọn chéo 100ml dung tích lớn (5 loại / 2 lựa chọn)",
            "sale_price": 25830,
            "sale_percent": 79,
            "purchase_count": 8321,
            "price": 123000,
            "productEtcInfo": {},
            "seller": {
                "address1": "",
                "address2": "",
                "bookmark_count": 0,
                "business_info": {
                    "business_code": "",
                    "business_name": "",
                    "mail_order_business_code": "",
                    "representative_name": ""
                },
                "email": "",
                "en_name": "",
                "id": "",
                "image_url": "",
                "name": "",
                "operation_time": "",
                "tags": null,
                "telephone": "",
                "text": "",
                "type": {
                    "id": "",
                    "name": ""
                }
            },
            "add_info": null,
            "sid": 9819636
        },
        {
            "id": 11486,
            "thumbnail": "https://image.brandi.me/cproduct/2020/04/29/13605230_1588127079_image1_M.jpg",
            "name": "[1 + 1 / Thời gian có hạn] Perfect Lip Velvet Lip Tint",
            "sale_price": 31680,
            "sale_percent": 28,
            "purchase_count": 370,
            "price": 44000,
            "productEtcInfo": {},
            "seller": {
                "address1": "",
                "address2": "",
                "bookmark_count": 0,
                "business_info": {
                    "business_code": "",
                    "business_name": "",
                    "mail_order_business_code": "",
                    "representative_name": ""
                },
                "email": "",
                "en_name": "",
                "id": "",
                "image_url": "",
                "name": "",
                "operation_time": "",
                "tags": null,
                "telephone": "",
                "text": "",
                "type": {
                    "id": "",
                    "name": ""
                }
            },
            "add_info": null,
            "sid": 13605230
        },
        {
            "id": 10462,
            "thumbnail": "https://image.brandi.me/cproduct/2019/10/16/11188540_1571218208_image1_M.jpg",
            "name": "Hộp mực chuyên nghiệp Beauty Mermaid Auto MTS chuyên nghiệp (6 loại)",
            "sale_price": 31900,
            "price": 31900,
            "productEtcInfo": {},
            "seller": {
                "address1": "",
                "address2": "",
                "bookmark_count": 0,
                "business_info": {
                    "business_code": "",
                    "business_name": "",
                    "mail_order_business_code": "",
                    "representative_name": ""
                },
                "email": "",
                "en_name": "",
                "id": "",
                "image_url": "",
                "name": "",
                "operation_time": "",
                "tags": null,
                "telephone": "",
                "text": "",
                "type": {
                    "id": "",
                    "name": ""
                }
            },
            "add_info": null,
            "sid": 11188540
        },
        {
            "id": 10441,
            "thumbnail": "https://image.brandi.me/cproduct/2020/04/09/15348652_1586394530_image1_M.jpg",
            "name": "[Uniclub] Mặt nạ làm sạch tan chảy 50 tấm, 1 hộp",
            "sale_price": 31900,
            "purchase_count": 325,
            "price": 31900,
            "productEtcInfo": {},
            "seller": {
                "address1": "",
                "address2": "",
                "bookmark_count": 0,
                "business_info": {
                    "business_code": "",
                    "business_name": "",
                    "mail_order_business_code": "",
                    "representative_name": ""
                },
                "email": "",
                "en_name": "",
                "id": "",
                "image_url": "",
                "name": "",
                "operation_time": "",
                "tags": null,
                "telephone": "",
                "text": "",
                "type": {
                    "id": "",
                    "name": ""
                }
            },
            "add_info": null,
            "sid": 15348652
        },
        {
            "id": 10454,
            "thumbnail": "https://image.brandi.me/cproduct/2019/12/23/12549349_1577068929_image1_M.jpg",
            "name": "Bộ sưu tập các mảnh sao từ khách du lịch của Rom & Earth #Lrict Edition",
            "sale_price": 32250,
            "sale_percent": 25,
            "purchase_count": 155,
            "price": 43000,
            "productEtcInfo": {},
            "seller": {
                "address1": "",
                "address2": "",
                "bookmark_count": 0,
                "business_info": {
                    "business_code": "",
                    "business_name": "",
                    "mail_order_business_code": "",
                    "representative_name": ""
                },
                "email": "",
                "en_name": "",
                "id": "",
                "image_url": "",
                "name": "",
                "operation_time": "",
                "tags": null,
                "telephone": "",
                "text": "",
                "type": {
                    "id": "",
                    "name": ""
                }
            },
            "add_info": null,
            "sid": 12549349
        },
        {
            "id": 10465,
            "thumbnail": "https://image.brandi.me/cproduct/2020/03/11/14474274_1583913537_image1_M.jpg",
            "name": "[Hera] Bột gợi cảm Matt số 435 Pampas 5g + [5 bộ bổ sung Age Away Simple Set]",
            "sale_price": 38500,
            "purchase_count": 25,
            "price": 38500,
            "productEtcInfo": {},
            "seller": {
                "address1": "",
                "address2": "",
                "bookmark_count": 0,
                "business_info": {
                    "business_code": "",
                    "business_name": "",
                    "mail_order_business_code": "",
                    "representative_name": ""
                },
                "email": "",
                "en_name": "",
                "id": "",
                "image_url": "",
                "name": "",
                "operation_time": "",
                "tags": null,
                "telephone": "",
                "text": "",
                "type": {
                    "id": "",
                    "name": ""
                }
            },
            "add_info": null,
            "sid": 14474274
        },
        {
            "id": 10460,
            "thumbnail": "https://image.brandi.me/cproduct/2020/04/14/15481944_1586832604_image1_M.jpg",
            "name": "[Vodana] Vodana x S the Set You Mini ủi Plan",
            "sale_price": 45471,
            "sale_percent": 31,
            "price": 65900,
            "productEtcInfo": {},
            "seller": {
                "address1": "",
                "address2": "",
                "bookmark_count": 0,
                "business_info": {
                    "business_code": "",
                    "business_name": "",
                    "mail_order_business_code": "",
                    "representative_name": ""
                },
                "email": "",
                "en_name": "",
                "id": "",
                "image_url": "",
                "name": "",
                "operation_time": "",
                "tags": null,
                "telephone": "",
                "text": "",
                "type": {
                    "id": "",
                    "name": ""
                }
            },
            "add_info": null,
            "sid": 15481944
        }
    ],
    "Method": "GET",
    "Status": "OK",
    "Success": true
}